{
    "nodes": [
        {
            "body": [
                {
                    "body": [
                        {
                            "body": [
                                {
                                    "left": {
                                        "default_value": null,
                                        "node_type": "Var",
                                        "source_refs": [
                                            {
                                                "col_end": 15,
                                                "col_start": 8,
                                                "node_type": "SourceRef",
                                                "row_end": 9,
                                                "row_start": 9,
                                                "source_file_name": "t03_protect_elderly"
                                            }
                                        ],
                                        "type": "float",
                                        "val": {
                                            "id": 7,
                                            "name": "elderly",
                                            "node_type": "Name",
                                            "source_refs": [
                                                {
                                                    "col_end": 15,
                                                    "col_start": 8,
                                                    "node_type": "SourceRef",
                                                    "row_end": 9,
                                                    "row_start": 9,
                                                    "source_file_name": "t03_protect_elderly"
                                                }
                                            ]
                                        }
                                    },
                                    "node_type": "Assignment",
                                    "right": {
                                        "interpreter": "Python",
                                        "node_type": "Operator",
                                        "op": "ast.Gt",
                                        "operands": [
                                            {
                                                "attr": {
                                                    "id": 9,
                                                    "name": "age",
                                                    "node_type": "Name",
                                                    "source_refs": [
                                                        {
                                                            "col_end": 32,
                                                            "col_start": 18,
                                                            "node_type": "SourceRef",
                                                            "row_end": 9,
                                                            "row_start": 9,
                                                            "source_file_name": "t03_protect_elderly"
                                                        }
                                                    ]
                                                },
                                                "node_type": "Attribute",
                                                "source_refs": [
                                                    {
                                                        "col_end": 32,
                                                        "col_start": 18,
                                                        "node_type": "SourceRef",
                                                        "row_end": 9,
                                                        "row_start": 9,
                                                        "source_file_name": "t03_protect_elderly"
                                                    }
                                                ],
                                                "value": {
                                                    "attr": {
                                                        "id": 8,
                                                        "name": "people",
                                                        "node_type": "Name",
                                                        "source_refs": [
                                                            {
                                                                "col_end": 28,
                                                                "col_start": 18,
                                                                "node_type": "SourceRef",
                                                                "row_end": 9,
                                                                "row_start": 9,
                                                                "source_file_name": "t03_protect_elderly"
                                                            }
                                                        ]
                                                    },
                                                    "node_type": "Attribute",
                                                    "source_refs": [
                                                        {
                                                            "col_end": 28,
                                                            "col_start": 18,
                                                            "node_type": "SourceRef",
                                                            "row_end": 9,
                                                            "row_start": 9,
                                                            "source_file_name": "t03_protect_elderly"
                                                        }
                                                    ],
                                                    "value": {
                                                        "id": 4,
                                                        "name": "sim",
                                                        "node_type": "Name",
                                                        "source_refs": [
                                                            {
                                                                "col_end": 21,
                                                                "col_start": 18,
                                                                "node_type": "SourceRef",
                                                                "row_end": 9,
                                                                "row_start": 9,
                                                                "source_file_name": "t03_protect_elderly"
                                                            }
                                                        ]
                                                    }
                                                }
                                            },
                                            {
                                                "node_type": "LiteralValue",
                                                "source_code_data_type": [
                                                    "Python",
                                                    "3.8",
                                                    "<class 'int'>"
                                                ],
                                                "source_refs": [
                                                    {
                                                        "col_end": 35,
                                                        "col_start": 33,
                                                        "node_type": "SourceRef",
                                                        "row_end": 9,
                                                        "row_start": 9,
                                                        "source_file_name": "t03_protect_elderly"
                                                    }
                                                ],
                                                "value": 70,
                                                "value_type": "Integer"
                                            }
                                        ],
                                        "source_language": "Python",
                                        "source_refs": [
                                            {
                                                "col_end": 35,
                                                "col_start": 18,
                                                "node_type": "SourceRef",
                                                "row_end": 9,
                                                "row_start": 9,
                                                "source_file_name": "t03_protect_elderly"
                                            }
                                        ],
                                        "version": "3.8.18"
                                    },
                                    "source_refs": [
                                        {
                                            "col_end": 35,
                                            "col_start": 8,
                                            "node_type": "SourceRef",
                                            "row_end": 9,
                                            "row_start": 9,
                                            "source_file_name": "t03_protect_elderly"
                                        }
                                    ]
                                },
                                {
                                    "left": {
                                        "default_value": null,
                                        "node_type": "Var",
                                        "source_refs": [
                                            {
                                                "col_end": 41,
                                                "col_start": 8,
                                                "node_type": "SourceRef",
                                                "row_end": 10,
                                                "row_start": 10,
                                                "source_file_name": "t03_protect_elderly"
                                            }
                                        ],
                                        "type": "Any",
                                        "val": {
                                            "attr": {
                                                "id": 10,
                                                "name": "rel_sus",
                                                "node_type": "Name",
                                                "source_refs": [
                                                    {
                                                        "col_end": 26,
                                                        "col_start": 8,
                                                        "node_type": "SourceRef",
                                                        "row_end": 10,
                                                        "row_start": 10,
                                                        "source_file_name": "t03_protect_elderly"
                                                    }
                                                ]
                                            },
                                            "node_type": "Attribute",
                                            "source_refs": [
                                                {
                                                    "col_end": 26,
                                                    "col_start": 8,
                                                    "node_type": "SourceRef",
                                                    "row_end": 10,
                                                    "row_start": 10,
                                                    "source_file_name": "t03_protect_elderly"
                                                }
                                            ],
                                            "value": {
                                                "attr": {
                                                    "id": 8,
                                                    "name": "people",
                                                    "node_type": "Name",
                                                    "source_refs": [
                                                        {
                                                            "col_end": 18,
                                                            "col_start": 8,
                                                            "node_type": "SourceRef",
                                                            "row_end": 10,
                                                            "row_start": 10,
                                                            "source_file_name": "t03_protect_elderly"
                                                        }
                                                    ]
                                                },
                                                "node_type": "Attribute",
                                                "source_refs": [
                                                    {
                                                        "col_end": 18,
                                                        "col_start": 8,
                                                        "node_type": "SourceRef",
                                                        "row_end": 10,
                                                        "row_start": 10,
                                                        "source_file_name": "t03_protect_elderly"
                                                    }
                                                ],
                                                "value": {
                                                    "id": 4,
                                                    "name": "sim",
                                                    "node_type": "Name",
                                                    "source_refs": [
                                                        {
                                                            "col_end": 11,
                                                            "col_start": 8,
                                                            "node_type": "SourceRef",
                                                            "row_end": 10,
                                                            "row_start": 10,
                                                            "source_file_name": "t03_protect_elderly"
                                                        }
                                                    ]
                                                }
                                            }
                                        }
                                    },
                                    "node_type": "Assignment",
                                    "right": {
                                        "arguments": [
                                            {
                                                "attr": {
                                                    "id": 10,
                                                    "name": "rel_sus",
                                                    "node_type": "Name",
                                                    "source_refs": [
                                                        {
                                                            "col_end": 26,
                                                            "col_start": 8,
                                                            "node_type": "SourceRef",
                                                            "row_end": 10,
                                                            "row_start": 10,
                                                            "source_file_name": "t03_protect_elderly"
                                                        }
                                                    ]
                                                },
                                                "node_type": "Attribute",
                                                "source_refs": [
                                                    {
                                                        "col_end": 26,
                                                        "col_start": 8,
                                                        "node_type": "SourceRef",
                                                        "row_end": 10,
                                                        "row_start": 10,
                                                        "source_file_name": "t03_protect_elderly"
                                                    }
                                                ],
                                                "value": {
                                                    "attr": {
                                                        "id": 8,
                                                        "name": "people",
                                                        "node_type": "Name",
                                                        "source_refs": [
                                                            {
                                                                "col_end": 18,
                                                                "col_start": 8,
                                                                "node_type": "SourceRef",
                                                                "row_end": 10,
                                                                "row_start": 10,
                                                                "source_file_name": "t03_protect_elderly"
                                                            }
                                                        ]
                                                    },
                                                    "node_type": "Attribute",
                                                    "source_refs": [
                                                        {
                                                            "col_end": 18,
                                                            "col_start": 8,
                                                            "node_type": "SourceRef",
                                                            "row_end": 10,
                                                            "row_start": 10,
                                                            "source_file_name": "t03_protect_elderly"
                                                        }
                                                    ],
                                                    "value": {
                                                        "id": 4,
                                                        "name": "sim",
                                                        "node_type": "Name",
                                                        "source_refs": [
                                                            {
                                                                "col_end": 11,
                                                                "col_start": 8,
                                                                "node_type": "SourceRef",
                                                                "row_end": 10,
                                                                "row_start": 10,
                                                                "source_file_name": "t03_protect_elderly"
                                                            }
                                                        ]
                                                    }
                                                }
                                            },
                                            {
                                                "id": 7,
                                                "name": "elderly",
                                                "node_type": "Name",
                                                "source_refs": [
                                                    {
                                                        "col_end": 34,
                                                        "col_start": 27,
                                                        "node_type": "SourceRef",
                                                        "row_end": 10,
                                                        "row_start": 10,
                                                        "source_file_name": "t03_protect_elderly"
                                                    }
                                                ]
                                            },
                                            {
                                                "node_type": "LiteralValue",
                                                "source_code_data_type": [
                                                    "Python",
                                                    "3.8",
                                                    "<class 'float'>"
                                                ],
                                                "source_refs": [
                                                    {
                                                        "col_end": 41,
                                                        "col_start": 38,
                                                        "node_type": "SourceRef",
                                                        "row_end": 10,
                                                        "row_start": 10,
                                                        "source_file_name": "t03_protect_elderly"
                                                    }
                                                ],
                                                "value": 0.0,
                                                "value_type": "AbstractFloat"
                                            }
                                        ],
                                        "func": {
                                            "id": 11,
                                            "name": "_set",
                                            "node_type": "Name",
                                            "source_refs": [
                                                {
                                                    "col_end": 41,
                                                    "col_start": 8,
                                                    "node_type": "SourceRef",
                                                    "row_end": 10,
                                                    "row_start": 10,
                                                    "source_file_name": "t03_protect_elderly"
                                                }
                                            ]
                                        },
                                        "node_type": "Call",
                                        "source_language": null,
                                        "source_language_version": null,
                                        "source_refs": [
                                            {
                                                "col_end": 41,
                                                "col_start": 8,
                                                "node_type": "SourceRef",
                                                "row_end": 10,
                                                "row_start": 10,
                                                "source_file_name": "t03_protect_elderly"
                                            }
                                        ]
                                    },
                                    "source_refs": [
                                        {
                                            "col_end": 41,
                                            "col_start": 8,
                                            "node_type": "SourceRef",
                                            "row_end": 10,
                                            "row_start": 10,
                                            "source_file_name": "t03_protect_elderly"
                                        }
                                    ]
                                }
                            ],
                            "expr": {
                                "interpreter": "Python",
                                "node_type": "Operator",
                                "op": "ast.Eq",
                                "operands": [
                                    {
                                        "attr": {
                                            "id": 5,
                                            "name": "t",
                                            "node_type": "Name",
                                            "source_refs": [
                                                {
                                                    "col_end": 12,
                                                    "col_start": 7,
                                                    "node_type": "SourceRef",
                                                    "row_end": 8,
                                                    "row_start": 8,
                                                    "source_file_name": "t03_protect_elderly"
                                                }
                                            ]
                                        },
                                        "node_type": "Attribute",
                                        "source_refs": [
                                            {
                                                "col_end": 12,
                                                "col_start": 7,
                                                "node_type": "SourceRef",
                                                "row_end": 8,
                                                "row_start": 8,
                                                "source_file_name": "t03_protect_elderly"
                                            }
                                        ],
                                        "value": {
                                            "id": 4,
                                            "name": "sim",
                                            "node_type": "Name",
                                            "source_refs": [
                                                {
                                                    "col_end": 10,
                                                    "col_start": 7,
                                                    "node_type": "SourceRef",
                                                    "row_end": 8,
                                                    "row_start": 8,
                                                    "source_file_name": "t03_protect_elderly"
                                                }
                                            ]
                                        }
                                    },
                                    {
                                        "arguments": [
                                            {
                                                "node_type": "LiteralValue",
                                                "source_code_data_type": [
                                                    "Python",
                                                    "3.8",
                                                    "<class 'str'>"
                                                ],
                                                "source_refs": [
                                                    {
                                                        "col_end": 36,
                                                        "col_start": 24,
                                                        "node_type": "SourceRef",
                                                        "row_end": 8,
                                                        "row_start": 8,
                                                        "source_file_name": "t03_protect_elderly"
                                                    }
                                                ],
                                                "value": "2021-04-01",
                                                "value_type": "List"
                                            }
                                        ],
                                        "func": {
                                            "attr": {
                                                "id": 6,
                                                "name": "day",
                                                "node_type": "Name",
                                                "source_refs": [
                                                    {
                                                        "col_end": 23,
                                                        "col_start": 16,
                                                        "node_type": "SourceRef",
                                                        "row_end": 8,
                                                        "row_start": 8,
                                                        "source_file_name": "t03_protect_elderly"
                                                    }
                                                ]
                                            },
                                            "node_type": "Attribute",
                                            "source_refs": [
                                                {
                                                    "col_end": 23,
                                                    "col_start": 16,
                                                    "node_type": "SourceRef",
                                                    "row_end": 8,
                                                    "row_start": 8,
                                                    "source_file_name": "t03_protect_elderly"
                                                }
                                            ],
                                            "value": {
                                                "id": 4,
                                                "name": "sim",
                                                "node_type": "Name",
                                                "source_refs": [
                                                    {
                                                        "col_end": 19,
                                                        "col_start": 16,
                                                        "node_type": "SourceRef",
                                                        "row_end": 8,
                                                        "row_start": 8,
                                                        "source_file_name": "t03_protect_elderly"
                                                    }
                                                ]
                                            }
                                        },
                                        "node_type": "Call",
                                        "source_language": null,
                                        "source_language_version": null,
                                        "source_refs": [
                                            {
                                                "col_end": 37,
                                                "col_start": 16,
                                                "node_type": "SourceRef",
                                                "row_end": 8,
                                                "row_start": 8,
                                                "source_file_name": "t03_protect_elderly"
                                            }
                                        ]
                                    }
                                ],
                                "source_language": "Python",
                                "source_refs": [
                                    {
                                        "col_end": 37,
                                        "col_start": 7,
                                        "node_type": "SourceRef",
                                        "row_end": 8,
                                        "row_start": 8,
                                        "source_file_name": "t03_protect_elderly"
                                    }
                                ],
                                "version": "3.8.18"
                            },
                            "node_type": "ModelIf",
                            "orelse": [],
                            "source_refs": [
                                {
                                    "col_end": 41,
                                    "col_start": 4,
                                    "node_type": "SourceRef",
                                    "row_end": 10,
                                    "row_start": 8,
                                    "source_file_name": "t03_protect_elderly"
                                }
                            ]
                        }
                    ],
                    "func_args": [
                        {
                            "default_value": null,
                            "node_type": "Var",
                            "source_refs": [
                                {
                                    "col_end": 23,
                                    "col_start": 20,
                                    "node_type": "SourceRef",
                                    "row_end": 7,
                                    "row_start": 7,
                                    "source_file_name": "t03_protect_elderly"
                                }
                            ],
                            "type": "float",
                            "val": {
                                "id": 4,
                                "name": "sim",
                                "node_type": "Name",
                                "source_refs": [
                                    {
                                        "col_end": 23,
                                        "col_start": 20,
                                        "node_type": "SourceRef",
                                        "row_end": 7,
                                        "row_start": 7,
                                        "source_file_name": "t03_protect_elderly"
                                    }
                                ]
                            }
                        }
                    ],
                    "name": {
                        "id": 3,
                        "name": "protect_elderly",
                        "node_type": "Name",
                        "source_refs": [
                            {
                                "col_end": 41,
                                "col_start": 0,
                                "node_type": "SourceRef",
                                "row_end": 10,
                                "row_start": 7,
                                "source_file_name": "t03_protect_elderly"
                            }
                        ]
                    },
                    "node_type": "FunctionDef",
                    "source_refs": [
                        {
                            "col_end": 41,
                            "col_start": 0,
                            "node_type": "SourceRef",
                            "row_end": 10,
                            "row_start": 7,
                            "source_file_name": "t03_protect_elderly"
                        }
                    ]
                },
                {
                    "left": {
                        "default_value": null,
                        "node_type": "Var",
                        "source_refs": [
                            {
                                "col_end": 4,
                                "col_start": 0,
                                "node_type": "SourceRef",
                                "row_end": 12,
                                "row_start": 12,
                                "source_file_name": "t03_protect_elderly"
                            }
                        ],
                        "type": "float",
                        "val": {
                            "id": 0,
                            "name": "pars",
                            "node_type": "Name",
                            "source_refs": [
                                {
                                    "col_end": 4,
                                    "col_start": 0,
                                    "node_type": "SourceRef",
                                    "row_end": 12,
                                    "row_start": 12,
                                    "source_file_name": "t03_protect_elderly"
                                }
                            ]
                        }
                    },
                    "node_type": "Assignment",
                    "right": {
                        "node_type": "LiteralValue",
                        "source_code_data_type": [
                            "Python",
                            "3.8",
                            "<class 'dict'>"
                        ],
                        "source_refs": [
                            {
                                "col_end": 47,
                                "col_start": 7,
                                "node_type": "SourceRef",
                                "row_end": 12,
                                "row_start": 12,
                                "source_file_name": "t03_protect_elderly"
                            }
                        ],
                        "value": "[('start_day', '2021-03-01'), ('n_days', 120)]",
                        "value_type": "Map"
                    },
                    "source_refs": [
                        {
                            "col_end": 47,
                            "col_start": 0,
                            "node_type": "SourceRef",
                            "row_end": 12,
                            "row_start": 12,
                            "source_file_name": "t03_protect_elderly"
                        }
                    ]
                },
                {
                    "left": {
                        "default_value": null,
                        "node_type": "Var",
                        "source_refs": [
                            {
                                "col_end": 2,
                                "col_start": 0,
                                "node_type": "SourceRef",
                                "row_end": 13,
                                "row_start": 13,
                                "source_file_name": "t03_protect_elderly"
                            }
                        ],
                        "type": "float",
                        "val": {
                            "id": 1,
                            "name": "s1",
                            "node_type": "Name",
                            "source_refs": [
                                {
                                    "col_end": 2,
                                    "col_start": 0,
                                    "node_type": "SourceRef",
                                    "row_end": 13,
                                    "row_start": 13,
                                    "source_file_name": "t03_protect_elderly"
                                }
                            ]
                        }
                    },
                    "node_type": "Assignment",
                    "right": {
                        "arguments": [
                            {
                                "id": 0,
                                "name": "pars",
                                "node_type": "Name",
                                "source_refs": [
                                    {
                                        "col_end": 16,
                                        "col_start": 12,
                                        "node_type": "SourceRef",
                                        "row_end": 13,
                                        "row_start": 13,
                                        "source_file_name": "t03_protect_elderly"
                                    }
                                ]
                            },
                            {
                                "left": {
                                    "default_value": null,
                                    "node_type": "Var",
                                    "source_refs": [
                                        {
                                            "col_end": 34,
                                            "col_start": 5,
                                            "node_type": "SourceRef",
                                            "row_end": 13,
                                            "row_start": 13,
                                            "source_file_name": "t03_protect_elderly"
                                        }
                                    ],
                                    "type": "float",
                                    "val": {
                                        "id": 100,
                                        "name": "label",
                                        "node_type": "Name",
                                        "source_refs": [
                                            {
                                                "col_end": 34,
                                                "col_start": 5,
                                                "node_type": "SourceRef",
                                                "row_end": 13,
                                                "row_start": 13,
                                                "source_file_name": "t03_protect_elderly"
                                            }
                                        ]
                                    }
                                },
                                "node_type": "Assignment",
                                "right": {
                                    "node_type": "LiteralValue",
                                    "source_code_data_type": [
                                        "Python",
                                        "3.8",
                                        "<class 'str'>"
                                    ],
                                    "source_refs": [
                                        {
                                            "col_end": 33,
                                            "col_start": 24,
                                            "node_type": "SourceRef",
                                            "row_end": 13,
                                            "row_start": 13,
                                            "source_file_name": "t03_protect_elderly"
                                        }
                                    ],
                                    "value": "Default",
                                    "value_type": "List"
                                },
                                "source_refs": [
                                    {
                                        "col_end": 34,
                                        "col_start": 5,
                                        "node_type": "SourceRef",
                                        "row_end": 13,
                                        "row_start": 13,
                                        "source_file_name": "t03_protect_elderly"
                                    }
                                ]
                            }
                        ],
                        "func": {
                            "attr": {
                                "id": 12,
                                "name": "Sim",
                                "node_type": "Name",
                                "source_refs": [
                                    {
                                        "col_end": 11,
                                        "col_start": 5,
                                        "node_type": "SourceRef",
                                        "row_end": 13,
                                        "row_start": 13,
                                        "source_file_name": "t03_protect_elderly"
                                    }
                                ]
                            },
                            "node_type": "Attribute",
                            "source_refs": [
                                {
                                    "col_end": 11,
                                    "col_start": 5,
                                    "node_type": "SourceRef",
                                    "row_end": 13,
                                    "row_start": 13,
                                    "source_file_name": "t03_protect_elderly"
                                }
                            ],
                            "value": {
                                "id": -1,
                                "name": "covasim",
                                "node_type": "Name",
                                "source_refs": [
                                    {
                                        "col_end": 7,
                                        "col_start": 5,
                                        "node_type": "SourceRef",
                                        "row_end": 13,
                                        "row_start": 13,
                                        "source_file_name": "t03_protect_elderly"
                                    }
                                ]
                            }
                        },
                        "node_type": "Call",
                        "source_language": null,
                        "source_language_version": null,
                        "source_refs": [
                            {
                                "col_end": 34,
                                "col_start": 5,
                                "node_type": "SourceRef",
                                "row_end": 13,
                                "row_start": 13,
                                "source_file_name": "t03_protect_elderly"
                            }
                        ]
                    },
                    "source_refs": [
                        {
                            "col_end": 34,
                            "col_start": 0,
                            "node_type": "SourceRef",
                            "row_end": 13,
                            "row_start": 13,
                            "source_file_name": "t03_protect_elderly"
                        }
                    ]
                },
                {
                    "left": {
                        "default_value": null,
                        "node_type": "Var",
                        "source_refs": [
                            {
                                "col_end": 2,
                                "col_start": 0,
                                "node_type": "SourceRef",
                                "row_end": 14,
                                "row_start": 14,
                                "source_file_name": "t03_protect_elderly"
                            }
                        ],
                        "type": "float",
                        "val": {
                            "id": 2,
                            "name": "s2",
                            "node_type": "Name",
                            "source_refs": [
                                {
                                    "col_end": 2,
                                    "col_start": 0,
                                    "node_type": "SourceRef",
                                    "row_end": 14,
                                    "row_start": 14,
                                    "source_file_name": "t03_protect_elderly"
                                }
                            ]
                        }
                    },
                    "node_type": "Assignment",
                    "right": {
                        "arguments": [
                            {
                                "id": 0,
                                "name": "pars",
                                "node_type": "Name",
                                "source_refs": [
                                    {
                                        "col_end": 16,
                                        "col_start": 12,
                                        "node_type": "SourceRef",
                                        "row_end": 14,
                                        "row_start": 14,
                                        "source_file_name": "t03_protect_elderly"
                                    }
                                ]
                            },
                            {
                                "left": {
                                    "default_value": null,
                                    "node_type": "Var",
                                    "source_refs": [
                                        {
                                            "col_end": 77,
                                            "col_start": 5,
                                            "node_type": "SourceRef",
                                            "row_end": 14,
                                            "row_start": 14,
                                            "source_file_name": "t03_protect_elderly"
                                        }
                                    ],
                                    "type": "float",
                                    "val": {
                                        "id": 100,
                                        "name": "label",
                                        "node_type": "Name",
                                        "source_refs": [
                                            {
                                                "col_end": 77,
                                                "col_start": 5,
                                                "node_type": "SourceRef",
                                                "row_end": 14,
                                                "row_start": 14,
                                                "source_file_name": "t03_protect_elderly"
                                            }
                                        ]
                                    }
                                },
                                "node_type": "Assignment",
                                "right": {
                                    "node_type": "LiteralValue",
                                    "source_code_data_type": [
                                        "Python",
                                        "3.8",
                                        "<class 'str'>"
                                    ],
                                    "source_refs": [
                                        {
                                            "col_end": 45,
                                            "col_start": 24,
                                            "node_type": "SourceRef",
                                            "row_end": 14,
                                            "row_start": 14,
                                            "source_file_name": "t03_protect_elderly"
                                        }
                                    ],
                                    "value": "Protect the elderly",
                                    "value_type": "List"
                                },
                                "source_refs": [
                                    {
                                        "col_end": 77,
                                        "col_start": 5,
                                        "node_type": "SourceRef",
                                        "row_end": 14,
                                        "row_start": 14,
                                        "source_file_name": "t03_protect_elderly"
                                    }
                                ]
                            },
                            {
                                "left": {
                                    "default_value": null,
                                    "node_type": "Var",
                                    "source_refs": [
                                        {
                                            "col_end": 77,
                                            "col_start": 5,
                                            "node_type": "SourceRef",
                                            "row_end": 14,
                                            "row_start": 14,
                                            "source_file_name": "t03_protect_elderly"
                                        }
                                    ],
                                    "type": "float",
                                    "val": {
                                        "id": 100,
                                        "name": "interventions",
                                        "node_type": "Name",
                                        "source_refs": [
                                            {
                                                "col_end": 77,
                                                "col_start": 5,
                                                "node_type": "SourceRef",
                                                "row_end": 14,
                                                "row_start": 14,
                                                "source_file_name": "t03_protect_elderly"
                                            }
                                        ]
                                    }
                                },
                                "node_type": "Assignment",
                                "right": {
                                    "id": 13,
                                    "name": "protect_elderly",
                                    "node_type": "Name",
                                    "source_refs": [
                                        {
                                            "col_end": 76,
                                            "col_start": 61,
                                            "node_type": "SourceRef",
                                            "row_end": 14,
                                            "row_start": 14,
                                            "source_file_name": "t03_protect_elderly"
                                        }
                                    ]
                                },
                                "source_refs": [
                                    {
                                        "col_end": 77,
                                        "col_start": 5,
                                        "node_type": "SourceRef",
                                        "row_end": 14,
                                        "row_start": 14,
                                        "source_file_name": "t03_protect_elderly"
                                    }
                                ]
                            }
                        ],
                        "func": {
                            "attr": {
                                "id": 12,
                                "name": "Sim",
                                "node_type": "Name",
                                "source_refs": [
                                    {
                                        "col_end": 11,
                                        "col_start": 5,
                                        "node_type": "SourceRef",
                                        "row_end": 14,
                                        "row_start": 14,
                                        "source_file_name": "t03_protect_elderly"
                                    }
                                ]
                            },
                            "node_type": "Attribute",
                            "source_refs": [
                                {
                                    "col_end": 11,
                                    "col_start": 5,
                                    "node_type": "SourceRef",
                                    "row_end": 14,
                                    "row_start": 14,
                                    "source_file_name": "t03_protect_elderly"
                                }
                            ],
                            "value": {
                                "id": -1,
                                "name": "covasim",
                                "node_type": "Name",
                                "source_refs": [
                                    {
                                        "col_end": 7,
                                        "col_start": 5,
                                        "node_type": "SourceRef",
                                        "row_end": 14,
                                        "row_start": 14,
                                        "source_file_name": "t03_protect_elderly"
                                    }
                                ]
                            }
                        },
                        "node_type": "Call",
                        "source_language": null,
                        "source_language_version": null,
                        "source_refs": [
                            {
                                "col_end": 77,
                                "col_start": 5,
                                "node_type": "SourceRef",
                                "row_end": 14,
                                "row_start": 14,
                                "source_file_name": "t03_protect_elderly"
                            }
                        ]
                    },
                    "source_refs": [
                        {
                            "col_end": 77,
                            "col_start": 0,
                            "node_type": "SourceRef",
                            "row_end": 14,
                            "row_start": 14,
                            "source_file_name": "t03_protect_elderly"
                        }
                    ]
                },
                {
                    "body": [
                        {
                            "arguments": [
                                {
                                    "left": {
                                        "default_value": null,
                                        "node_type": "Var",
                                        "source_refs": [
                                            {
                                                "col_end": 70,
                                                "col_start": 4,
                                                "node_type": "SourceRef",
                                                "row_end": 17,
                                                "row_start": 17,
                                                "source_file_name": "t03_protect_elderly"
                                            }
                                        ],
                                        "type": "float",
                                        "val": {
                                            "id": 100,
                                            "name": "to_plot",
                                            "node_type": "Name",
                                            "source_refs": [
                                                {
                                                    "col_end": 70,
                                                    "col_start": 4,
                                                    "node_type": "SourceRef",
                                                    "row_end": 17,
                                                    "row_start": 17,
                                                    "source_file_name": "t03_protect_elderly"
                                                }
                                            ]
                                        }
                                    },
                                    "node_type": "Assignment",
                                    "right": {
                                        "node_type": "LiteralValue",
                                        "source_code_data_type": [
                                            "Python",
                                            "3.8",
                                            "List"
                                        ],
                                        "source_refs": [
                                            {
                                                "col_end": 69,
                                                "col_start": 37,
                                                "node_type": "SourceRef",
                                                "row_end": 17,
                                                "row_start": 17,
                                                "source_file_name": "t03_protect_elderly"
                                            }
                                        ],
                                        "value": [
                                            {
                                                "node_type": "LiteralValue",
                                                "source_code_data_type": [
                                                    "Python",
                                                    "3.8",
                                                    "<class 'str'>"
                                                ],
                                                "source_refs": [
                                                    {
                                                        "col_end": 50,
                                                        "col_start": 38,
                                                        "node_type": "SourceRef",
                                                        "row_end": 17,
                                                        "row_start": 17,
                                                        "source_file_name": "t03_protect_elderly"
                                                    }
                                                ],
                                                "value": "cum_deaths",
                                                "value_type": "List"
                                            },
                                            {
                                                "node_type": "LiteralValue",
                                                "source_code_data_type": [
                                                    "Python",
                                                    "3.8",
                                                    "<class 'str'>"
                                                ],
                                                "source_refs": [
                                                    {
                                                        "col_end": 68,
                                                        "col_start": 52,
                                                        "node_type": "SourceRef",
                                                        "row_end": 17,
                                                        "row_start": 17,
                                                        "source_file_name": "t03_protect_elderly"
                                                    }
                                                ],
                                                "value": "cum_infections",
                                                "value_type": "List"
                                            }
                                        ],
                                        "value_type": "List"
                                    },
                                    "source_refs": [
                                        {
                                            "col_end": 70,
                                            "col_start": 4,
                                            "node_type": "SourceRef",
                                            "row_end": 17,
                                            "row_start": 17,
                                            "source_file_name": "t03_protect_elderly"
                                        }
                                    ]
                                }
                            ],
                            "func": {
                                "attr": {
                                    "id": 16,
                                    "name": "plot",
                                    "node_type": "Name",
                                    "source_refs": [
                                        {
                                            "col_end": 28,
                                            "col_start": 4,
                                            "node_type": "SourceRef",
                                            "row_end": 17,
                                            "row_start": 17,
                                            "source_file_name": "t03_protect_elderly"
                                        }
                                    ]
                                },
                                "node_type": "Attribute",
                                "source_refs": [
                                    {
                                        "col_end": 28,
                                        "col_start": 4,
                                        "node_type": "SourceRef",
                                        "row_end": 17,
                                        "row_start": 17,
                                        "source_file_name": "t03_protect_elderly"
                                    }
                                ],
                                "value": {
                                    "arguments": [
                                        {
                                            "id": 1,
                                            "name": "s1",
                                            "node_type": "Name",
                                            "source_refs": [
                                                {
                                                    "col_end": 18,
                                                    "col_start": 16,
                                                    "node_type": "SourceRef",
                                                    "row_end": 17,
                                                    "row_start": 17,
                                                    "source_file_name": "t03_protect_elderly"
                                                }
                                            ]
                                        },
                                        {
                                            "id": 2,
                                            "name": "s2",
                                            "node_type": "Name",
                                            "source_refs": [
                                                {
                                                    "col_end": 22,
                                                    "col_start": 20,
                                                    "node_type": "SourceRef",
                                                    "row_end": 17,
                                                    "row_start": 17,
                                                    "source_file_name": "t03_protect_elderly"
                                                }
                                            ]
                                        }
                                    ],
                                    "func": {
                                        "attr": {
                                            "id": 15,
                                            "name": "parallel",
                                            "node_type": "Name",
                                            "source_refs": [
                                                {
                                                    "col_end": 15,
                                                    "col_start": 4,
                                                    "node_type": "SourceRef",
                                                    "row_end": 17,
                                                    "row_start": 17,
                                                    "source_file_name": "t03_protect_elderly"
                                                }
                                            ]
                                        },
                                        "node_type": "Attribute",
                                        "source_refs": [
                                            {
                                                "col_end": 15,
                                                "col_start": 4,
                                                "node_type": "SourceRef",
                                                "row_end": 17,
                                                "row_start": 17,
                                                "source_file_name": "t03_protect_elderly"
                                            }
                                        ],
                                        "value": {
                                            "id": -1,
                                            "name": "covasim",
                                            "node_type": "Name",
                                            "source_refs": [
                                                {
                                                    "col_end": 6,
                                                    "col_start": 4,
                                                    "node_type": "SourceRef",
                                                    "row_end": 17,
                                                    "row_start": 17,
                                                    "source_file_name": "t03_protect_elderly"
                                                }
                                            ]
                                        }
                                    },
                                    "node_type": "Call",
                                    "source_language": null,
                                    "source_language_version": null,
                                    "source_refs": [
                                        {
                                            "col_end": 23,
                                            "col_start": 4,
                                            "node_type": "SourceRef",
                                            "row_end": 17,
                                            "row_start": 17,
                                            "source_file_name": "t03_protect_elderly"
                                        }
                                    ]
                                }
                            },
                            "node_type": "Call",
                            "source_language": null,
                            "source_language_version": null,
                            "source_refs": [
                                {
                                    "col_end": 70,
                                    "col_start": 4,
                                    "node_type": "SourceRef",
                                    "row_end": 17,
                                    "row_start": 17,
                                    "source_file_name": "t03_protect_elderly"
                                }
                            ]
                        }
                    ],
                    "expr": {
                        "interpreter": "Python",
                        "node_type": "Operator",
                        "op": "ast.Eq",
                        "operands": [
                            {
                                "id": 14,
                                "name": "__name__",
                                "node_type": "Name",
                                "source_refs": [
                                    {
                                        "col_end": 11,
                                        "col_start": 3,
                                        "node_type": "SourceRef",
                                        "row_end": 16,
                                        "row_start": 16,
                                        "source_file_name": "t03_protect_elderly"
                                    }
                                ]
                            },
                            {
                                "node_type": "LiteralValue",
                                "source_code_data_type": [
                                    "Python",
                                    "3.8",
                                    "<class 'str'>"
                                ],
                                "source_refs": [
                                    {
                                        "col_end": 25,
                                        "col_start": 15,
                                        "node_type": "SourceRef",
                                        "row_end": 16,
                                        "row_start": 16,
                                        "source_file_name": "t03_protect_elderly"
                                    }
                                ],
                                "value": "__main__",
                                "value_type": "List"
                            }
                        ],
                        "source_language": "Python",
                        "source_refs": [
                            {
                                "col_end": 25,
                                "col_start": 3,
                                "node_type": "SourceRef",
                                "row_end": 16,
                                "row_start": 16,
                                "source_file_name": "t03_protect_elderly"
                            }
                        ],
                        "version": "3.8.18"
                    },
                    "node_type": "ModelIf",
                    "orelse": [],
                    "source_refs": [
                        {
                            "col_end": 70,
                            "col_start": 0,
                            "node_type": "SourceRef",
                            "row_end": 17,
                            "row_start": 16,
                            "source_file_name": "t03_protect_elderly"
                        }
                    ]
                }
            ],
            "name": "t03_protect_elderly",
            "node_type": "Module",
            "source_refs": [
                {
                    "col_end": null,
                    "col_start": null,
                    "node_type": "SourceRef",
                    "row_end": 17,
                    "row_start": 1,
                    "source_file_name": "t03_protect_elderly.py"
                }
            ]
        }
    ]
}